django_macros_url-0.3.0.dist-info/DESCRIPTION.rst
django_macros_url-0.3.0.dist-info/METADATA
django_macros_url-0.3.0.dist-info/RECORD
django_macros_url-0.3.0.dist-info/WHEEL
django_macros_url-0.3.0.dist-info/metadata.json
django_macros_url-0.3.0.dist-info/pbr.json
django_macros_url-0.3.0.dist-info/top_level.txt
macrosurl/__init__.py
